glacier_backup/__init__.py
glacier_backup/backup.py
glacier_backup/db.py
glacier_backup/uploader.py
glacier_backup-1.2.dist-info/LICENSE
glacier_backup-1.2.dist-info/METADATA
glacier_backup-1.2.dist-info/WHEEL
glacier_backup-1.2.dist-info/entry_points.txt
glacier_backup-1.2.dist-info/top_level.txt
glacier_backup-1.2.dist-info/RECORD
